pydantic_ai_utcp-0.1.0.dist-info/METADATA
pydantic_ai_utcp-0.1.0.dist-info/WHEEL
pydantic_ai_utcp-0.1.0.dist-info/entry_points.txt
pydantic_ai_utcp-0.1.0.dist-info/licenses/LICENSE
pydantic_utcp_adapters/__init__.py
pydantic_utcp_adapters/pydantic_bedrock.py
pydantic_utcp_adapters/pydantic_tools.py
pydantic_ai_utcp-0.1.0.dist-info/RECORD
