Metadata-Version: 2.4
Name: pydantic-ai-utcp
Version: 0.1.0
Summary: Make Universal Tool Calling Protocol (UTCP) tools compatible with Pydantic AI.
Author: UTCP Contributors
License-Expression: MIT
Project-URL: Homepage, https://github.com/universal-tool-calling-protocol/pydantic-ai-utcp
Project-URL: Documentation, https://github.com/universal-tool-calling-protocol/pydantic-ai-utcp#readme
Project-URL: Repository, https://github.com/universal-tool-calling-protocol/pydantic-ai-utcp
Project-URL: Issues, https://github.com/universal-tool-calling-protocol/pydantic-ai-utcp/issues
Requires-Python: >=3.11
Requires-Dist: pydantic==2.11.7
Requires-Dist: Authlib==1.6.1
Requires-Dist: python-dotenv==1.0.1
Requires-Dist: tomli==2.2.1
Requires-Dist: aiohttp==3.12.13
Requires-Dist: gql==3.5.3
Requires-Dist: PyYAML==6.0.2
Requires-Dist: build==1.3.0
Requires-Dist: pytest==8.4.1
Requires-Dist: pytest-asyncio==1.1.0
Requires-Dist: pytest-aiohttp==1.1.0
Requires-Dist: pytest-cov==6.2.1
Requires-Dist: coverage==7.10.3
Requires-Dist: fastapi==0.115.0
Requires-Dist: uvicorn==0.35.0
Requires-Dist: utcp>=1.0.4
Requires-Dist: utcp-http>=1.0.4
Requires-Dist: utcp-text>=1.0.2
Provides-Extra: dev
Requires-Dist: build; extra == "dev"
Requires-Dist: twine; extra == "dev"
